egehelperforschool4/ЕГЭ.py
egehelperforschool4-1.2.dist-info/METADATA
egehelperforschool4-1.2.dist-info/WHEEL
egehelperforschool4-1.2.dist-info/top_level.txt
egehelperforschool4-1.2.dist-info/RECORD
