Metadata-Version: 2.1
Name: egehelperforschool4
Version: 1.2
Summary: vack
Author: Apchixba02
Author-email: kiri.nadymov2017@yandex.ru
Classifier: Programming Language :: Python :: 3
Classifier: License :: OSI Approved :: MIT License
Classifier: Operating System :: OS Independent
Requires-Python: >=3.6
